README.md
setup.cfg
setup.py
pyhmtai/__init__.py
pyhmtai/hmtai.py
pyhmtai.egg-info/PKG-INFO
pyhmtai.egg-info/SOURCES.txt
pyhmtai.egg-info/dependency_links.txt
pyhmtai.egg-info/top_level.txt
pyhmtai/api/__init__.py
pyhmtai/api/http.py
pyhmtai/data/__init__.py
pyhmtai/data/constants.py
pyhmtai/data/exceptions.py
pyhmtai/data/routes/__init__.py
pyhmtai/data/routes/nsfw.py
pyhmtai/data/routes/sfw.py
pyhmtai/impl/__init__.py
pyhmtai/impl/http.py