Metadata-Version: 2.1
Name: pyhmtai
Version: 0.1.6
Summary: HMtai python port.
Home-page: https://github.com/MagM1go/pyhmtai
Author: MagMigo
Requires-Python: >=3.7
